ntv/__init__.py
ntv/ntv-cli
ntv/shortcuts.py
ntv/web.py
ntv-0.4.4.data/scripts/ntv-cli
ntv-0.4.4.dist-info/DESCRIPTION.rst
ntv-0.4.4.dist-info/METADATA
ntv-0.4.4.dist-info/RECORD
ntv-0.4.4.dist-info/WHEEL
ntv-0.4.4.dist-info/metadata.json
ntv-0.4.4.dist-info/top_level.txt
