Metadata-Version: 2.0
Name: ntv
Version: 0.4.4
Summary: n.tv api
Home-page: https://github.com/onjin/ntv
Author: Marek Wywiał
Author-email: onjinx@gmail.com
License: BSD
Keywords: ntv
Platform: UNKNOWN
Classifier: Development Status :: 2 - Pre-Alpha
Classifier: Intended Audience :: Developers
Classifier: License :: OSI Approved :: BSD License
Classifier: Natural Language :: English
Classifier: Programming Language :: Python :: 2
Classifier: Programming Language :: Python :: 2.6
Classifier: Programming Language :: Python :: 2.7
Classifier: Programming Language :: Python :: 3
Classifier: Programming Language :: Python :: 3.3
Requires-Dist: baker
Requires-Dist: clint
Requires-Dist: requests
Requires-Dist: requests-cache
Requires-Dist: simplejson
